tred/__init__.py
tred/_m_transforms.py
tred/_tensor_ops.py
tred/_tensor_pca.py
tred/_utils.py
tred/datasets/__init__.py
tred-0.1.4.dist-info/METADATA
tred-0.1.4.dist-info/WHEEL
tred-0.1.4.dist-info/licenses/LICENSE
tred-0.1.4.dist-info/RECORD
