Metadata-Version: 2.3
Name: tred
Version: 0.1.4
Summary: Dimensionality reduction techniques for order-3 tensors
Project-URL: Homepage, https://github.com/brendanlu/tred
Project-URL: Issues, https://github.com/brendanlu/tred/issues
Author-email: Brendan Lu <brendannlu5@gmail.com>
License-File: LICENSE
Classifier: License :: OSI Approved :: BSD License
Classifier: Operating System :: OS Independent
Classifier: Programming Language :: Python :: 3
Classifier: Topic :: Scientific/Engineering :: Mathematics
Requires-Python: >=3.8
Requires-Dist: scikit-learn>=1.3.2
